{"authorUserId": "889856", "description": "I got back into watching anime recently, and I found Angel Beats. Loving the main character's theme, I decided to make a cover for it for my instrument. I plan on making a full orchestral when I get the time, and if you guys want, I can possibly try to create a piano cover. Thanks for your support!", "instrumentsNames": ["Viola"], "title": "Angel Beats-Otonashi's Theme Viola Arrangement", "url": "/user/889856/scores/1014116", "partsCount": "1", "revisionId": "1397526", "pagesCount": "1", "partsNames": ["Viola"], "timeUpdated": "2018-07-16 08:59:41 UTC", "instrumentsCount": "1", "duration": "99", "timeCreated": "2015-06-29 02:23:03 UTC", "id": "1014116", "__key__": {"namespace": "", "app": "s~xmader", "path": "\"musescore-scoreinfo\", \"1014116\"", "kind": "musescore-scoreinfo", "name": "1014116"}, "__error__": [], "__has_error__": false, "musicxmlInstruments": []}