{"authorUserId": "874", "description": "", "instrumentsNames": [], "title": "Ciao", "url": "/user/874/scores/1026", "partsCount": "1", "revisionId": "1309", "pagesCount": "1", "partsNames": [], "timeUpdated": "2010-10-28 08:33:09 UTC", "instrumentsCount": "0", "duration": "24", "timeCreated": "2010-10-28 08:29:07 UTC", "id": "1026", "__key__": {"namespace": "", "app": "s~xmader", "path": "\"musescore-scoreinfo\", \"1026\"", "kind": "musescore-scoreinfo", "name": "1026"}, "__error__": [], "__has_error__": false, "musicxmlInstruments": []}