{"authorUserId": "3540", "description": "These lines will work on Gm7, C7, F#7alt, Bflat Lydian,Dmin7 Aeolian,Em7flat5", "instrumentsNames": [], "title": "Hexatonic Study", "url": "/user/3540/scores/102990", "partsCount": "1", "revisionId": "140553", "pagesCount": "1", "partsNames": ["Electric Guitar"], "timeUpdated": "2018-07-16 08:57:44 UTC", "instrumentsCount": "0", "duration": "64", "timeCreated": "2013-04-26 12:03:24 UTC", "id": "102990", "__key__": {"namespace": "", "app": "s~xmader", "path": "\"musescore-scoreinfo\", \"102990\"", "kind": "musescore-scoreinfo", "name": "102990"}, "__error__": [], "__has_error__": false, "musicxmlInstruments": []}