{"authorUserId": "3627366", "description": "", "instrumentsNames": ["Piano(5)"], "title": "LOVE YOU ONLY", "url": "/user/3627366/scores/1031586", "partsCount": "5", "revisionId": "1432271", "pagesCount": "14", "partsNames": ["Piano", "Piano", "Piano", "Piano", "Piano"], "timeUpdated": "2018-07-16 08:59:48 UTC", "instrumentsCount": "1", "duration": "196", "timeCreated": "2015-07-07 02:23:54 UTC", "id": "1031586", "__key__": {"namespace": "", "app": "s~xmader", "path": "\"musescore-scoreinfo\", \"1031586\"", "kind": "musescore-scoreinfo", "name": "1031586"}, "__error__": [], "__has_error__": false, "musicxmlInstruments": []}