{"authorUserId": "3510051", "description": "", "instrumentsNames": ["Alto Saxophone"], "title": "NONCEPAC", "url": "/user/3510051/scores/1013086", "partsCount": "1", "revisionId": "1395746", "pagesCount": "3", "partsNames": ["Sassofono contralto"], "timeUpdated": "2018-07-16 08:59:40 UTC", "instrumentsCount": "1", "duration": "338", "timeCreated": "2015-06-28 17:06:08 UTC", "id": "1013086", "__key__": {"namespace": "", "app": "s~xmader", "path": "\"musescore-scoreinfo\", \"1013086\"", "kind": "musescore-scoreinfo", "name": "1013086"}, "__error__": [], "__has_error__": false, "musicxmlInstruments": [], "ms3_metadata": {"arranger": "", "composer": "", "copyright": "", "creationDate": "2015-06-28", "lyricist": "", "movementNumber": "", "movementTitle": "", "mscVersion": "3.02", "originalFormat": "mid", "platform": "Microsoft Windows", "poet": "", "source": "", "translator": "", "workNumber": "", "workTitle": "", "musescore": "3.6.2", "last_mc": 169, "last_mn": 169, "length_qb": 676.0, "length_qb_unfolded": 676.0, "label_count": 0, "TimeSig": {"1": "4/4"}, "KeySig": {"1": -1}, "all_notes_qb": 626.2, "n_onsets": 668, "n_onset_positions": 668, "parts": {"part_1": {"staves": [1], "trackName": "Sassofono contralto", "longName": "Sassofono contralto", "shortName": "Sax. a.", "instrument": "Sassofono contralto", "staff_1_ambitus": {"min_midi": 58, "min_name": "Bb3", "max_midi": 77, "max_name": "F5"}}}, "ambitus": {"min_midi": 58, "min_name": "Bb3", "max_midi": 77, "max_name": "F5"}}, "musescore_metadata": {"metadata": {"composer": "", "duration": 338, "fileVersion": 302, "hasHarmonies": "false", "hasLyrics": "false", "keysig": -4, "lyrics": "", "measures": 169, "mscoreVersion": "3.6.2", "pageFormat": {"height": 297, "twosided": "true", "width": 210}, "pages": 3, "parts": [{"harmonyCount": 0, "hasDrumStaff": "false", "hasPitchedStaff": "true", "hasTabStaff": "false", "instrumentId": "wind.reed.saxophone.alto", "isVisible": "true", "lyricCount": 0, "name": "Sassofono contralto", "program": 65}], "poet": "", "previousSource": "", "subtitle": "", "tempo": 120, "tempoText": "<sym>metNoteQuarterUp</sym> = 120", "textFramesData": {"composers": [], "poets": [], "subtitles": [], "titles": []}, "timesig": "4/4", "title": "1013086"}}, "__terminated__": true}