{"authorUserId": "77714", "description": "", "instrumentsNames": ["Violin", "Oboe", "Cello", "Contrabass"], "title": "Song For Friends ++ July 24th 11:06 AM 2015", "url": "/user/77714/scores/1018641", "partsCount": "4", "revisionId": "1731276", "pagesCount": "6", "partsNames": ["Violin", "Oboe", "Violoncello", "Double Bass"], "timeUpdated": "2019-02-09 13:51:50 UTC", "instrumentsCount": "4", "duration": "369", "timeCreated": "2015-07-01 04:53:46 UTC", "id": "1018641", "__key__": {"namespace": "", "app": "s~xmader", "path": "\"musescore-scoreinfo\", \"1018641\"", "kind": "musescore-scoreinfo", "name": "1018641"}, "__error__": [], "__has_error__": false, "musicxmlInstruments": [], "first_composer": "unknown"}