{"authorUserId": "3549941", "description": "stuff", "instrumentsNames": ["Guitar(2)", "Bass", "Piano", "Percussion"], "title": "First Song", "url": "/user/3549941/scores/1018326", "partsCount": "5", "revisionId": "1404866", "pagesCount": "34", "partsNames": ["Electric Guitar", "Bass Guitar", "Piano", "Drumset", "Electric Guitar"], "timeUpdated": "2018-07-16 08:59:42 UTC", "instrumentsCount": "4", "duration": "218", "timeCreated": "2015-07-01 01:25:08 UTC", "id": "1018326", "__key__": {"namespace": "", "app": "s~xmader", "path": "\"musescore-scoreinfo\", \"1018326\"", "kind": "musescore-scoreinfo", "name": "1018326"}, "__error__": [], "__has_error__": false, "musicxmlInstruments": [], "__terminated__": true, "last_error": "Score.__init__() got an unexpected keyword argument 'level'", "ms3_metadata": {"arranger": "", "composer": "Kailas Rajan", "copyright": "Powertrain", "creationDate": "2015-06-08", "lyricist": "Powertrain", "movementNumber": "", "movementTitle": "", "mscVersion": "3.02", "platform": "Apple Macintosh", "poet": "", "source": "", "translator": "", "workNumber": "", "workTitle": "Trial", "partName": "Rhythm Guitar", "title_text": "First Song\n", "subtitle_text": "A trial", "composer_text": "Kailas Rajan", "lyricist_text": "Powertrain", "part_name_text": "Piano; Drums; Lead Guitar; Rhythm Guitar; Bass", "musescore": "3.6.2", "last_mc": 137, "last_mn": 137, "length_qb": 576.0, "length_qb_unfolded": 576.0, "label_count": 0, "TimeSig": {"1": "4/4"}, "KeySig": {"1": 0}, "all_notes_qb": 1024.0, "n_onsets": 1568, "n_onset_positions": 784, "parts": {"part_1": {"staves": [1], "trackName": "Electric Guitar [Tablature]", "longName": "Electric Guitar", "shortName": "El. Guit.", "instrument": "Electric Guitar [Tablature]", "staff_1_ambitus": {"min_midi": 40, "min_name": "E2", "max_midi": 55, "max_name": "G3"}}, "part_2": {"staves": [2], "trackName": "Bass Guitar [Tablature]", "longName": "Bass Guitar", "shortName": "B. Guit.", "instrument": "Bass Guitar [Tablature]", "staff_2_ambitus": {}}, "part_3": {"staves": [3, 4], "trackName": "Piano", "longName": "Piano", "shortName": "Pno.", "instrument": "Piano", "staff_3_ambitus": {}, "staff_4_ambitus": {}}, "part_4": {"staves": [5], "trackName": "Drumset", "longName": "Drumset", "shortName": "Drs.", "instrument": "Drumset", "staff_5_ambitus": {}}, "part_5": {"staves": [6], "trackName": "Electric Guitar [Tablature]", "longName": "Electric Guitar", "shortName": "El. Guit.", "instrument": "Electric Guitar [Tablature]", "staff_6_ambitus": {}}, "part_6": {"staves": [1], "trackName": "", "longName": "Bass Guitar", "shortName": "B. Guit.", "instrument": "Bass Guitar [Tablature]", "staff_1_ambitus": {"min_midi": 40, "min_name": "E2", "max_midi": 55, "max_name": "G3"}}, "part_7": {"staves": [1], "trackName": "", "longName": "Electric Guitar", "shortName": "El. Guit.", "instrument": "Electric Guitar [Tablature]", "staff_1_ambitus": {"min_midi": 40, "min_name": "E2", "max_midi": 55, "max_name": "G3"}}, "part_8": {"staves": [1, 2], "trackName": "", "longName": "Piano", "shortName": "Pno.", "instrument": "Piano", "staff_1_ambitus": {"min_midi": 40, "min_name": "E2", "max_midi": 55, "max_name": "G3"}, "staff_2_ambitus": {}}, "part_9": {"staves": [1], "trackName": "", "longName": "Drumset", "shortName": "Drs.", "instrument": "Drumset", "staff_1_ambitus": {"min_midi": 40, "min_name": "E2", "max_midi": 55, "max_name": "G3"}}, "part_10": {"staves": [1], "trackName": "", "longName": "Electric Guitar", "shortName": "El. Guit.", "instrument": "Electric Guitar [Tablature]", "staff_1_ambitus": {"min_midi": 40, "min_name": "E2", "max_midi": 55, "max_name": "G3"}}}, "ambitus": {"min_midi": 40, "min_name": "E2", "max_midi": 55, "max_name": "G3"}}, "musescore_metadata": {"metadata": {"composer": "Kailas Rajan", "duration": 218, "fileVersion": 302, "hasHarmonies": "false", "hasLyrics": "false", "keysig": 0, "lyrics": "", "measures": 136, "mscoreVersion": "3.6.2", "pageFormat": {"height": 279, "twosided": "true", "width": 216}, "pages": 32, "parts": [{"harmonyCount": 0, "hasDrumStaff": "false", "hasPitchedStaff": "false", "hasTabStaff": "true", "instrumentId": "pluck.guitar.electric", "isVisible": "true", "lyricCount": 0, "name": "Electric Guitar", "program": 27}, {"harmonyCount": 0, "hasDrumStaff": "false", "hasPitchedStaff": "false", "hasTabStaff": "true", "instrumentId": "pluck.bass", "isVisible": "true", "lyricCount": 0, "name": "Bass Guitar", "program": 34}, {"harmonyCount": 0, "hasDrumStaff": "false", "hasPitchedStaff": "true", "hasTabStaff": "false", "instrumentId": "keyboard.piano", "isVisible": "true", "lyricCount": 0, "name": "Piano", "program": 0}, {"harmonyCount": 0, "hasDrumStaff": "true", "hasPitchedStaff": "false", "hasTabStaff": "false", "instrumentId": "drum.group.set", "isVisible": "true", "lyricCount": 0, "name": "Drumset", "program": 0}, {"harmonyCount": 0, "hasDrumStaff": "false", "hasPitchedStaff": "false", "hasTabStaff": "true", "instrumentId": "pluck.guitar.electric", "isVisible": "true", "lyricCount": 0, "name": "Electric Guitar", "program": 27}], "poet": "Powertrain", "previousSource": "", "subtitle": "A trial", "tempo": 150, "tempoText": "<sym>metNoteQuarterUp</sym> = 150", "textFramesData": {"composers": ["Kailas Rajan"], "poets": ["Powertrain"], "subtitles": ["A trial"], "titles": ["First Song\n"]}, "timesig": "4/4", "title": "First Song\n"}}, "first_composer": null}