{"authorUserId": "2768506", "description": "", "instrumentsNames": ["Voice", "Piano"], "title": "Der Lindenbaum", "url": "/user/2768506/scores/1019686", "partsCount": "2", "revisionId": "1407411", "pagesCount": "11", "partsNames": ["Voice", "Piano"], "timeUpdated": "2018-07-16 08:59:43 UTC", "instrumentsCount": "2", "duration": "159", "timeCreated": "2015-07-01 16:27:14 UTC", "id": "1019686", "__key__": {"namespace": "", "app": "s~xmader", "path": "\"musescore-scoreinfo\", \"1019686\"", "kind": "musescore-scoreinfo", "name": "1019686"}, "__error__": [], "__has_error__": false, "musicxmlInstruments": [], "ms3_metadata": {"arranger": "", "composer": "", "copyright": "", "creationDate": "2022-12-03", "lyricist": "", "movementNumber": "", "movementTitle": "", "mscVersion": "3.02", "platform": "Linux", "poet": "", "source": "", "translator": "", "workNumber": "", "workTitle": "", "title_text": "Der Lindenbaum", "composer_text": "Franz Schubert", "musescore": "3.6.2", "last_mc": 82, "last_mn": 82, "length_qb": 246.0, "length_qb_unfolded": 246.0, "label_count": 0, "TimeSig": {"1": "3/4"}, "KeySig": {"1": 4, "25": 1, "37": 4}, "all_notes_qb": 884.58, "n_onsets": 1651, "n_onset_positions": 776, "parts": {"part_1": {"staves": [1], "trackName": "Voice", "instrument": "Voice", "staff_1_ambitus": {"min_midi": 59, "min_name": "B3", "max_midi": 76, "max_name": "E5"}}, "part_2": {"staves": [2, 3], "trackName": "Piano", "instrument": "Piano", "staff_2_ambitus": {"min_midi": 47, "min_name": "B2", "max_midi": 80, "max_name": "G#5"}, "staff_3_ambitus": {"min_midi": 35, "min_name": "B1", "max_midi": 68, "max_name": "G#4"}}}, "ambitus": {"min_midi": 35, "min_name": "B1", "max_midi": 80, "max_name": "G#5"}}, "musescore_metadata": {"metadata": {"composer": "Franz Schubert", "duration": 132, "fileVersion": 302, "hasHarmonies": "false", "hasLyrics": "true", "keysig": 4, "lyrics": "Am Brunnen vor em Thore da steht ein Lindenbaum; ich tr\u00e4umt' in seinem Schatten so manchen s\u00fcssen Traum. Ich schnitt in seine Rinde so manches liebe Wort; es zog in Freund' und Leide zu ihmmich immer fort. Ich musst' auch heute wandern vorbei in tiefer Nacht, da hab' ich noch im Dunkel die Augen zugemacht. Und seine Zweige rauschten, als riefen sie mir zu: komm her zu mir, Geselle, hier find'st du deine Ruh! Die kalten Winde bliesen mir grad' in's Angesicht, der Hut flog mir vom Kopfe, ich wendete mich nicht. Nun bin ich manche Stunde entfernt von jenem Ort, und immer h\u00f6r' ich's rauschen! du f\u00e4ndest Ruhe dort! Nun bin ich manche Stunde entfernt von jenem Ort, und immer h\u00f6r' ich's rauschen: du f\u00e4ndest Ruhe dort, du f\u00e4ndest Ruhe dort!", "measures": 82, "mscoreVersion": "3.6.2", "pageFormat": {"height": 297, "twosided": "true", "width": 210}, "pages": 23, "parts": [{"harmonyCount": 0, "hasDrumStaff": "false", "hasPitchedStaff": "true", "hasTabStaff": "false", "instrumentId": "voice.vocals", "isVisible": "true", "lyricCount": 189, "name": "<font face=\"Times New Roman\"></font>Voice", "program": 52}, {"harmonyCount": 0, "hasDrumStaff": "false", "hasPitchedStaff": "true", "hasTabStaff": "false", "instrumentId": "keyboard.piano", "isVisible": "true", "lyricCount": 0, "name": "<font face=\"Times New Roman\"></font>Piano", "program": 0}], "poet": "", "previousSource": "", "subtitle": "", "tempo": 112, "tempoText": "<font face=\"Times New Roman\"></font><b>M\u00e4\u00dfig</b>", "textFramesData": {"composers": ["Franz Schubert"], "poets": [], "subtitles": [], "titles": ["Der Lindenbaum"]}, "timesig": "3/4", "title": "Der Lindenbaum"}}, "__terminated__": true}