{"authorUserId": "55706", "description": "Original Jazz Composition", "instrumentsNames": [], "title": "Jazzy Orange", "url": "/user/55706/scores/102164", "partsCount": "9", "revisionId": "139414", "pagesCount": "16", "partsNames": ["Alto Saxophone", "Tenor Saxophone", "Baritone Saxophone", "B? Trumpet", "Trombone", "Trombone", "Marimba", "Pedal Hi-hat", "Electric Bass"], "timeUpdated": "2018-07-16 08:57:42 UTC", "instrumentsCount": "0", "duration": "232", "timeCreated": "2013-04-21 22:11:53 UTC", "id": "102164", "__key__": {"namespace": "", "app": "s~xmader", "path": "\"musescore-scoreinfo\", \"102164\"", "kind": "musescore-scoreinfo", "name": "102164"}, "__error__": [], "__has_error__": false, "musicxmlInstruments": []}