{"authorUserId": "3400976", "description": "An original piece arranged for brass ensemble. This piece is still a work in progress so constructive criticism is appreciated. ", "instrumentsNames": ["Trumpet(2)", "French Horn", "Trombone", "Tuba"], "title": "The Warrior's Hymn Mvt. 1", "url": "/user/3400976/scores/1021191", "partsCount": "5", "revisionId": "1409791", "pagesCount": "3", "partsNames": ["B? Trumpet I", "B? Trumpet II", "Horn in F", "Trombone", "Tuba"], "timeUpdated": "2018-07-16 08:59:44 UTC", "instrumentsCount": "4", "duration": "62", "timeCreated": "2015-07-02 06:46:27 UTC", "id": "1021191", "__key__": {"namespace": "", "app": "s~xmader", "path": "\"musescore-scoreinfo\", \"1021191\"", "kind": "musescore-scoreinfo", "name": "1021191"}, "__error__": [], "__has_error__": false, "musicxmlInstruments": []}