{"authorUserId": "133902", "description": "", "instrumentsNames": ["Piano"], "title": "Aufstehn, aufeinander zugehn", "url": "/user/133902/scores/1023401", "partsCount": "1", "revisionId": "1413401", "pagesCount": "1", "partsNames": [], "timeUpdated": "2015-07-03 08:36:05 UTC", "instrumentsCount": "1", "duration": "54", "timeCreated": "2015-07-03 08:33:41 UTC", "id": "1023401", "__key__": {"namespace": "", "app": "s~xmader", "path": "\"musescore-scoreinfo\", \"1023401\"", "kind": "musescore-scoreinfo", "name": "1023401"}, "__error__": [], "__has_error__": false, "musicxmlInstruments": [], "ms3_metadata": {"arranger": "", "composer": "Musik:  Purple Schulz, Josef Piek, Clemens Bittlinger", "copyright": "", "creationDate": "2015-07-02", "lyricist": "Text: Clemens Bittlinger", "movementNumber": "", "movementTitle": "", "mscVersion": "3.02", "platform": "Apple Macintosh", "poet": "", "source": "", "translator": "", "workNumber": "", "workTitle": "Aufsteh'n, aufeinander zugeh'n", "title_text": "Aufstehn, aufeinander zugehn Musik:  Purple Schulz, Josef Piek, Clemens Bittlinger (+ T)       ", "musescore": "3.6.2", "last_mc": 27, "last_mn": 27, "length_qb": 108.0, "length_qb_unfolded": 108.0, "label_count": 33, "TimeSig": {"1": "4/4"}, "KeySig": {"1": 2}, "all_notes_qb": 90.0, "n_onsets": 105, "n_onset_positions": 105, "parts": {"part_1": {"staves": [1], "trackName": "Stimme", "longName": "Stimme", "shortName": "St.", "instrument": "Stimme", "staff_1_ambitus": {"min_midi": 57, "min_name": "A3", "max_midi": 74, "max_name": "D5"}}}, "ambitus": {"min_midi": 57, "min_name": "A3", "max_midi": 74, "max_name": "D5"}}, "musescore_metadata": {"metadata": {"composer": "Musik:  Purple Schulz, Josef Piek, Clemens Bittlinger", "duration": 54, "fileVersion": 302, "hasHarmonies": "true", "hasLyrics": "true", "keysig": 2, "lyrics": "Dab dab da be du da dap dap dap da be du da dap dap da be du da dap dap dap da be du da Wir wollen aufstehn, aufeinander zugehn, voneinander lernen, miteinander umzugehn. Aufstehn, aufeinander zugehn und uns nicht entfernen, wenn wir etwas nicht verstehn. 1.   Jeder hat was 1.   einzubringen, diese Vielfalt, wunderbar. 1.   Neue Lieder wolln wir singen, neue Texte 1.   laut und klar. Wir wollen 2.   Diese Welt ist 2.   uns gegeben, wir sind alle G\u00e4ste hier. 2.   Wenn wir nicht zusammenleben, kann die Menschheit 2.   nur verliern. 3.   Dass aus Fremden 3.   Nachbarn werden, das geschieht nicht von allein. 3.   Dass aus Nachbarn Freunde werden, daf\u00fcr setzen 3.   wir uns ein.", "measures": 27, "mscoreVersion": "3.6.2", "pageFormat": {"height": 297, "twosided": "true", "width": 210}, "pages": 1, "parts": [{"harmonyCount": 33, "hasDrumStaff": "false", "hasPitchedStaff": "true", "hasTabStaff": "false", "instrumentId": "voice.vocals", "isVisible": "true", "lyricCount": 164, "name": "Stimme", "program": 0}], "poet": "Text: Clemens Bittlinger", "previousSource": "", "subtitle": "", "tempo": 0, "tempoText": "", "textFramesData": {"composers": [], "poets": [], "subtitles": [], "titles": ["Aufstehn, aufeinander zugehn Musik:  Purple Schulz, Josef Piek, Clemens Bittlinger (+ T)       "]}, "timesig": "4/4", "title": "Aufstehn, aufeinander zugehn Musik:  Purple Schulz, Josef Piek, Clemens Bittlinger (+ T)       "}}, "__terminated__": true}