{"authorUserId": "3559986", "description": "", "instrumentsNames": ["Trumpet", "French Horn"], "title": "Rocky Theme for Trumpet and Horn", "url": "/user/3559986/scores/1025746", "partsCount": "2", "revisionId": "1420801", "pagesCount": "1", "partsNames": ["B? Trumpet", "Horn"], "timeUpdated": "2018-07-16 08:59:45 UTC", "instrumentsCount": "2", "duration": "51", "timeCreated": "2015-07-04 13:49:47 UTC", "id": "1025746", "__key__": {"namespace": "", "app": "s~xmader", "path": "\"musescore-scoreinfo\", \"1025746\"", "kind": "musescore-scoreinfo", "name": "1025746"}, "__error__": [], "__has_error__": false, "musicxmlInstruments": [], "__terminated__": true, "last_error": "Score.__init__() got an unexpected keyword argument 'level'", "ms3_metadata": {"arranger": "", "composer": "", "copyright": "", "creationDate": "2015-06-13", "lyricist": "", "movementNumber": "", "movementTitle": "", "mscVersion": "3.02", "platform": "Microsoft Windows", "poet": "", "source": "https://musescore.com/score/1025746", "translator": "", "workNumber": "", "workTitle": "", "title_text": "", "composer_text": "", "musescore": "3.6.2", "last_mc": 15, "last_mn": 15, "length_qb": 57.0, "length_qb_unfolded": 85.0, "label_count": 0, "TimeSig": {"1": "4/4"}, "KeySig": {"1": -2}, "all_notes_qb": 107.0, "n_onsets": 170, "n_onset_positions": 115, "parts": {"part_1": {"staves": [1], "trackName": "Bb Trumpet", "instrument": "Bb Trumpet", "staff_1_ambitus": {"min_midi": 60, "min_name": "C4", "max_midi": 75, "max_name": "Eb5"}}, "part_2": {"staves": [2], "trackName": "Horn", "instrument": "Horn", "staff_2_ambitus": {"min_midi": 44, "min_name": "Ab2", "max_midi": 60, "max_name": "C4"}}}, "ambitus": {"min_midi": 44, "min_name": "Ab2", "max_midi": 75, "max_name": "Eb5"}}, "musescore_metadata": {"metadata": {"composer": "Original arrangement by Nicholas Smith                                   Edited for Trumpet and Horn by someone else\n", "duration": 51, "fileVersion": 302, "hasHarmonies": "false", "hasLyrics": "false", "keysig": -4, "lyrics": "", "measures": 15, "mscoreVersion": "3.6.2", "pageFormat": {"height": 297, "twosided": "true", "width": 210}, "pages": 1, "parts": [{"harmonyCount": 0, "hasDrumStaff": "false", "hasPitchedStaff": "true", "hasTabStaff": "false", "instrumentId": "brass.cornet.soprano", "isVisible": "true", "lyricCount": 0, "name": "<font size=\"13.5337\"></font><font face=\"Times New Roman\"></font>B<font face=\"MScore1\"></font><sym>accidentalFlat</sym><font face=\"Times New Roman\"></font> Trumpet", "program": 56}, {"harmonyCount": 0, "hasDrumStaff": "false", "hasPitchedStaff": "true", "hasTabStaff": "false", "instrumentId": "brass.french-horn", "isVisible": "true", "lyricCount": 0, "name": "<font face=\"Times New Roman\"></font>Horn", "program": 60}], "poet": "", "previousSource": "https://musescore.com/score/1025746", "subtitle": "", "tempo": 100, "tempoText": "<i><font size=\"24\"></font><font face=\"Times New Roman\"></font><sym>metNoteQuarterUp</sym><font size=\"12\"></font> = 100</i>", "textFramesData": {"composers": ["Original arrangement by Nicholas Smith                                   Edited for Trumpet and Horn by someone else\n"], "poets": [], "subtitles": [], "titles": ["Rocky Theme"]}, "timesig": "4/4", "title": "Rocky Theme"}}, "first_composer": null}