{"authorUserId": "2624036", "description": "The main melody from the green greens stage written out for trombone.", "instrumentsNames": ["Trombone"], "title": "Green Greens from Kirby's Dreamland", "url": "/user/2624036/scores/1029421", "partsCount": "1", "revisionId": "1423841", "pagesCount": "1", "partsNames": ["Tenor Trombone"], "timeUpdated": "2018-07-16 08:59:47 UTC", "instrumentsCount": "1", "duration": "64", "timeCreated": "2015-07-06 02:57:55 UTC", "id": "1029421", "__key__": {"namespace": "", "app": "s~xmader", "path": "\"musescore-scoreinfo\", \"1029421\"", "kind": "musescore-scoreinfo", "name": "1029421"}, "__error__": [], "__has_error__": false, "musicxmlInstruments": [], "ms3_metadata": {"arranger": "", "composer": "Composer", "copyright": "", "creationDate": "", "lyricist": "", "movementNumber": "", "movementTitle": "", "mscVersion": "3.02", "platform": "Linux", "poet": "", "source": "", "translator": "", "workNumber": "", "workTitle": "Title", "title_text": "Green Greens\nKirby", "composer_text": "Jun Ishikawa", "musescore": "3.6.2", "last_mc": 32, "last_mn": 32, "length_qb": 128.0, "length_qb_unfolded": 128.0, "label_count": 0, "TimeSig": {"1": "4/4"}, "KeySig": {"1": -1}, "all_notes_qb": 69.0, "n_onsets": 88, "n_onset_positions": 88, "parts": {"part_1": {"staves": [1], "trackName": "Tenor Trombone", "longName": "Tenor Trombone", "shortName": "T. Trb.", "instrument": "Tenor Trombone", "staff_1_ambitus": {"min_midi": 48, "min_name": "C3", "max_midi": 65, "max_name": "F4"}}}, "ambitus": {"min_midi": 48, "min_name": "C3", "max_midi": 65, "max_name": "F4"}}, "musescore_metadata": {"metadata": {"composer": "Jun Ishikawa", "duration": 64, "fileVersion": 302, "hasHarmonies": "false", "hasLyrics": "false", "keysig": -1, "lyrics": "", "measures": 32, "mscoreVersion": "3.6.2", "pageFormat": {"height": 279, "twosided": "true", "width": 216}, "pages": 1, "parts": [{"harmonyCount": 0, "hasDrumStaff": "false", "hasPitchedStaff": "true", "hasTabStaff": "false", "instrumentId": "brass.trombone.tenor", "isVisible": "true", "lyricCount": 0, "name": "Tenor Trombone", "program": 57}], "poet": "", "previousSource": "", "subtitle": "", "tempo": 0, "tempoText": "", "textFramesData": {"composers": ["Jun Ishikawa"], "poets": [], "subtitles": [], "titles": ["Green Greens\nKirby"]}, "timesig": "4/4", "title": "Green Greens\nKirby"}}, "__terminated__": true}