{"authorUserId": "3395951", "description": "\"His attack on the windmills\" de la obra Don Quixote de Telemann para cuarteto de cuerda.", "instrumentsNames": ["Violin(2)", "Viola", "Cello"], "title": "His attack on the windmills", "url": "/user/3395951/scores/1034861", "partsCount": "4", "revisionId": "1433451", "pagesCount": "5", "partsNames": ["Violin I", "Violin II", "Viola", "Violoncello"], "timeUpdated": "2018-07-16 08:59:49 UTC", "instrumentsCount": "3", "duration": "144", "timeCreated": "2015-07-08 14:28:22 UTC", "id": "1034861", "__key__": {"namespace": "", "app": "s~xmader", "path": "\"musescore-scoreinfo\", \"1034861\"", "kind": "musescore-scoreinfo", "name": "1034861"}, "__error__": [], "__has_error__": false, "musicxmlInstruments": [], "__terminated__": true, "last_error": "/usr/lib/libjack.so.0\n/usr/lib/libnss3.so\nCreating main window\u2026\nReading translations\u2026\nconvert </home/hentsche/ComposersClassifier/data/mscz/1034861.mscz>...\nQZip: not a zip file!\nCannot read file /home/hentsche/ComposersClassifier/data/mscz/1034861.mscz:\n\n"}