{"authorUserId": "27381565", "description": "Ippolitov Procession of the Sardar Clarinet in A 2", "instrumentsNames": ["Voice"], "title": "Ippolitov Procession of the Sardar Clarinet in A 2", "url": "/user/27381565/scores/4871550", "partsCount": "1", "revisionId": "7951410", "pagesCount": "5", "partsNames": ["Part_1"], "timeUpdated": "2018-07-16 08:59:27 UTC", "instrumentsCount": "1", "duration": "198", "timeCreated": "2017-12-29 16:09:32 UTC", "id": "4871550", "__key__": {"namespace": "", "app": "s~xmader", "path": "\"musescore-scoreinfo\", \"4871550\"", "kind": "musescore-scoreinfo", "name": "4871550"}, "__error__": [], "__has_error__": false, "musicxmlInstruments": [], "__terminated__": true, "last_error": "'str' object has no attribute 'to_list'", "ms3_metadata": {"arranger": "", "composer": "Arranger: Henk Kox", "copyright": "C C", "creationDate": "2017-12-29", "lyricist": "Clarinet in A 2", "movementNumber": "", "movementTitle": "", "mscVersion": "3.02", "originalFormat": "xml", "platform": "Linux", "poet": "", "source": "/tmp/lg-402768977.tmp.pdf", "translator": "", "workNumber": "Allegro moderate, Tempo marziale (J = 72)", "workTitle": "", "composer_text": "1859-1935; Arranger: Henk Kox; I1; M1kl Ppoh", "lyricist_text": "Allegro moderate, Tempo marziale (J = 72); ; Clarinet in A 2", "title_text": "Sarc", "musescore": "3.6.2", "last_mc": 100, "last_mn": 100, "length_qb": 395.38, "length_qb_unfolded": 395.38, "label_count": 1, "TimeSig": {"1": "4/4", "52": "2/4", "65": "4/4"}, "KeySig": {"1": 1}, "all_notes_qb": 264.25, "n_onsets": 632, "n_onset_positions": 630, "parts": {"part_1": {"staves": [1], "trackName": "Part_1", "longName": "Part_1", "instrument": "Voice Oohs", "staff_1_ambitus": {"min_midi": 35, "min_name": "B1", "max_midi": 93, "max_name": "A6"}}}, "ambitus": {"min_midi": 35, "min_name": "B1", "max_midi": 93, "max_name": "A6"}}, "musescore_metadata": {"metadata": {"composer": "M1kl Ppoh", "duration": 198, "fileVersion": 302, "hasHarmonies": "true", "hasLyrics": "false", "keysig": 1, "lyrics": "", "measures": 100, "mscoreVersion": "3.6.2", "pageFormat": {"height": 297, "twosided": "false", "width": 210}, "pages": 5, "parts": [{"harmonyCount": 1, "hasDrumStaff": "false", "hasPitchedStaff": "true", "hasTabStaff": "false", "instrumentId": "voice.vocals", "isVisible": "true", "lyricCount": 0, "name": "Part_1", "program": 53}], "poet": "Clarinet in A 2", "previousSource": "/tmp/lg-402768977.tmp.pdf", "subtitle": "", "tempo": 120, "tempoText": "<sym>metNoteQuarterUp</sym> = 120", "textFramesData": {"composers": ["M1kl Ppoh", "I1", "1859-1935", "Arranger: Henk Kox"], "poets": ["Clarinet in A 2", "Allegro moderate, Tempo marziale (J = 72)", "10"], "subtitles": [], "titles": ["Sarc"]}, "timesig": "4/4", "title": "Sarc"}}}